AISTLAB_nitrotyper-0.6.10.dist-info/DESCRIPTION.rst
AISTLAB_nitrotyper-0.6.10.dist-info/METADATA
AISTLAB_nitrotyper-0.6.10.dist-info/RECORD
AISTLAB_nitrotyper-0.6.10.dist-info/WHEEL
AISTLAB_nitrotyper-0.6.10.dist-info/entry_points.txt
AISTLAB_nitrotyper-0.6.10.dist-info/metadata.json
AISTLAB_nitrotyper-0.6.10.dist-info/top_level.txt
nitrotyper/__init__.py
nitrotyper/example.py
nitrotyper/nitrotyper.py
nitrotyper/data/chars.json
