Metadata-Version: 2.0
Name: AISTLAB-nitrotyper
Version: 0.6.10
Summary: https://www.nitrotype.com auto typer
Home-page: https://github.com/winxos/nitrotyper
Author: winxos
Author-email: winxos@hotmail.com
License: MIT License
Keywords: nitrotype,winxos,AISTLAB
Platform: UNKNOWN
Classifier: Development Status :: 4 - Beta
Classifier: Intended Audience :: End Users/Desktop
Classifier: Topic :: Games/Entertainment
Classifier: Programming Language :: Python :: 3
Classifier: Programming Language :: Python :: 3.2
Classifier: Programming Language :: Python :: 3.3
Classifier: Programming Language :: Python :: 3.4
Classifier: Programming Language :: Python :: 3.5
Classifier: Programming Language :: Python :: 3.6
Requires-Dist: opencv-python
Requires-Dist: pyautogui
